cawdrey/__init__.py
cawdrey/_bdict.py
cawdrey/_bdict.pyi
cawdrey/_frozendict.py
cawdrey/alphadict.py
cawdrey/base.py
cawdrey/frozenordereddict.py
cawdrey/header_mapping.py
cawdrey/nonelessdict.py
cawdrey/py.typed
cawdrey/tally.py
cawdrey/utils.py
cawdrey-0.5.1.dist-info/LICENSE
cawdrey-0.5.1.dist-info/METADATA
cawdrey-0.5.1.dist-info/WHEEL
cawdrey-0.5.1.dist-info/entry_points.txt
cawdrey-0.5.1.dist-info/RECORD
