Metadata-Version: 2.1
Name: cawdrey
Version: 0.5.1
Summary: Several useful custom dictionaries for Python 📖 🐍
Author-email: Dominic Davis-Foster <dominic@davis-foster.co.uk>
License: LGPL-3.0-or-later
Keywords: Counter,dict,dictionary,frozen,frozendict,frozenordereddict,immutable,Mapping,MappingProxyType,map,orderedfrozendict
Home-page: https://github.com/domdfcoding/cawdrey
Project-URL: Issue Tracker, https://github.com/domdfcoding/cawdrey/issues
Project-URL: Source Code, https://github.com/domdfcoding/cawdrey
Project-URL: Documentation, https://cawdrey.readthedocs.io/en/latest
Platform: Windows
Platform: macOS
Platform: Linux
Classifier: Development Status :: 4 - Beta
Classifier: Intended Audience :: Developers
Classifier: License :: OSI Approved :: GNU Lesser General Public License v3 or later (LGPLv3+)
Classifier: Operating System :: OS Independent
Classifier: Programming Language :: Python
Classifier: Programming Language :: Python :: 3 :: Only
Classifier: Programming Language :: Python :: 3.6
Classifier: Programming Language :: Python :: 3.7
Classifier: Programming Language :: Python :: 3.8
Classifier: Programming Language :: Python :: 3.9
Classifier: Programming Language :: Python :: 3.10
Classifier: Programming Language :: Python :: 3.11
Classifier: Programming Language :: Python :: 3.12
Classifier: Programming Language :: Python :: Implementation :: CPython
Classifier: Programming Language :: Python :: Implementation :: PyPy
Classifier: Topic :: Software Development :: Libraries :: Python Modules
Classifier: Topic :: Utilities
Classifier: Typing :: Typed
Requires-Python: >=3.6
Requires-Dist: domdf-python-tools>=1.1.0
Requires-Dist: typing-extensions>=3.7.4.3
